r00server/__init__.py
r00server/client.py
r00server/server.py
r00server/utils.py
r00server-0.1.1.dist-info/METADATA
r00server-0.1.1.dist-info/WHEEL
r00server-0.1.1.dist-info/RECORD
