Metadata-Version: 2.4
Name: r00server
Version: 0.1.1
Requires-Python: >=3.10
Requires-Dist: aiofiles
Requires-Dist: fastapi
Requires-Dist: niquests
Requires-Dist: platformdirs
Requires-Dist: python-multipart
Requires-Dist: r00logger
Requires-Dist: uvicorn[standard]
